{
	"cmake" : 
	{
		"generator" : 
		{
			"multiConfig" : false,
			"name" : "Ninja"
		},
		"paths" : 
		{
			"cmake" : "/Users/b/Applications/CLion.app/Contents/bin/cmake/mac/aarch64/bin/cmake",
			"cpack" : "/Users/b/Applications/CLion.app/Contents/bin/cmake/mac/aarch64/bin/cpack",
			"ctest" : "/Users/b/Applications/CLion.app/Contents/bin/cmake/mac/aarch64/bin/ctest",
			"root" : "/Users/b/Applications/CLion.app/Contents/bin/cmake/mac/aarch64/share/cmake-3.27"
		},
		"version" : 
		{
			"isDirty" : false,
			"major" : 3,
			"minor" : 27,
			"patch" : 8,
			"string" : "3.27.8",
			"suffix" : ""
		}
	},
	"objects" : 
	[
		{
			"jsonFile" : "codemodel-v2-c7454120c70bfd5d8625.json",
			"kind" : "codemodel",
			"version" : 
			{
				"major" : 2,
				"minor" : 6
			}
		},
		{
			"jsonFile" : "cache-v2-666b782677c48d4dd7d2.json",
			"kind" : "cache",
			"version" : 
			{
				"major" : 2,
				"minor" : 0
			}
		},
		{
			"jsonFile" : "cmakeFiles-v1-d29e4286daa049c2d224.json",
			"kind" : "cmakeFiles",
			"version" : 
			{
				"major" : 1,
				"minor" : 0
			}
		},
		{
			"jsonFile" : "toolchains-v1-6f619f6ed2b9cb9d1698.json",
			"kind" : "toolchains",
			"version" : 
			{
				"major" : 1,
				"minor" : 0
			}
		}
	],
	"reply" : 
	{
		"cache-v2" : 
		{
			"jsonFile" : "cache-v2-666b782677c48d4dd7d2.json",
			"kind" : "cache",
			"version" : 
			{
				"major" : 2,
				"minor" : 0
			}
		},
		"cmakeFiles-v1" : 
		{
			"jsonFile" : "cmakeFiles-v1-d29e4286daa049c2d224.json",
			"kind" : "cmakeFiles",
			"version" : 
			{
				"major" : 1,
				"minor" : 0
			}
		},
		"codemodel-v2" : 
		{
			"jsonFile" : "codemodel-v2-c7454120c70bfd5d8625.json",
			"kind" : "codemodel",
			"version" : 
			{
				"major" : 2,
				"minor" : 6
			}
		},
		"toolchains-v1" : 
		{
			"jsonFile" : "toolchains-v1-6f619f6ed2b9cb9d1698.json",
			"kind" : "toolchains",
			"version" : 
			{
				"major" : 1,
				"minor" : 0
			}
		}
	}
}
